md_translate/__init__.py
md_translate/application.py
md_translate/document/__init__.py
md_translate/document/blocks.py
md_translate/document/document.py
md_translate/document/parser.py
md_translate/exceptions.py
md_translate/main.py
md_translate/settings/__init__.py
md_translate/settings/_base_settings.py
md_translate/settings/_settings_to_cli.py
md_translate/translators/__init__.py
md_translate/translators/_api_base.py
md_translate/translators/_base_translator.py
md_translate/translators/_selenium_base.py
md_translate/translators/bing.py
md_translate/translators/deepl.py
md_translate/translators/deepl_api.py
md_translate/translators/google.py
md_translate/translators/libretranslate.py
md_translate/translators/randomizer/__init__.py
md_translate/translators/randomizer/const.py
md_translate/translators/randomizer/randomizer.py
md_translate/translators/yandex.py
md_translate-3.4.0.dist-info/LICENSE
md_translate-3.4.0.dist-info/METADATA
md_translate-3.4.0.dist-info/WHEEL
md_translate-3.4.0.dist-info/entry_points.txt
md_translate-3.4.0.dist-info/RECORD
