Metadata-Version: 2.1
Name: md_translate
Version: 3.4.0
Summary: CLI tool to translate markdown files
Home-page: https://github.com/ilyachch/md_docs-trans-app
License: MIT
Author: Ilya Chichak
Author-email: ilyachch@gmail.com
Requires-Python: >=3.10,<4.0
Classifier: Development Status :: 4 - Beta
Classifier: Environment :: Console
Classifier: Intended Audience :: Developers
Classifier: Intended Audience :: End Users/Desktop
Classifier: License :: OSI Approved :: MIT License
Classifier: Operating System :: Microsoft :: Windows
Classifier: Operating System :: POSIX :: Linux
Classifier: Programming Language :: Python
Classifier: Programming Language :: Python :: 3
Classifier: Programming Language :: Python :: 3.10
Classifier: Programming Language :: Python :: 3.11
Classifier: Programming Language :: Python :: 3.12
Classifier: Programming Language :: Python :: 3.13
Classifier: Programming Language :: Python :: 3 :: Only
Classifier: Topic :: Documentation
Classifier: Topic :: Utilities
Classifier: Typing :: Typed
Requires-Dist: click (>=8.1.3,<9.0.0)
Requires-Dist: mistune (>=2.0.4,<3.0.0)
Requires-Dist: pydantic (>=1.10.2,<2.0.0)
Requires-Dist: selenium (>=4.5.0,<5.0.0)
Requires-Dist: webdriver-manager (>=4.0.0,<5.0.0)
Project-URL: Repository, https://github.com/ilyachch/md_docs-trans-app
